ao3_cli/__init__.py
ao3_cli/cli.py
ao3_cli/utils/__init__.py
ao3_cli/utils/ao3.py
ao3_cli/utils/fetch_data.py
ao3_cli/utils/logging.py
ao3_cli/utils/processing.py
ao3_cli-0.1.6.dist-info/LICENSE.txt
ao3_cli-0.1.6.dist-info/METADATA
ao3_cli-0.1.6.dist-info/WHEEL
ao3_cli-0.1.6.dist-info/entry_points.txt
ao3_cli-0.1.6.dist-info/top_level.txt
ao3_cli-0.1.6.dist-info/RECORD
