Metadata-Version: 2.1
Name: ao3-cli
Version: 0.1.6
Summary: A CLI to download from archiveofourown.org
Home-page: https://github.com/arzkar/ao3-cli/
Author: Arbaaz Laskar
Author-email: arzkar.dev@gmail.com
License: Apache License
Classifier: Programming Language :: Python :: 3
Classifier: License :: OSI Approved :: Apache Software License
Classifier: Operating System :: OS Independent
License-File: LICENSE.txt
Requires-Dist: click (>=7.1.2)
Requires-Dist: rich (>=10.3.0)
Requires-Dist: requests (>=2.25.1)
Requires-Dist: loguru (>=0.6.0)
Requires-Dist: tqdm (>=4.60.0)
Requires-Dist: BeautifulSoup4 (>=4.9.3)
Requires-Dist: colorama (>=0.4.4)
